nautobot_device_lifecycle_mgmt/__init__.py
nautobot_device_lifecycle_mgmt/api/__init__.py
nautobot_device_lifecycle_mgmt/api/serializers.py
nautobot_device_lifecycle_mgmt/api/urls.py
nautobot_device_lifecycle_mgmt/api/views.py
nautobot_device_lifecycle_mgmt/app-config-schema.json
nautobot_device_lifecycle_mgmt/banner.py
nautobot_device_lifecycle_mgmt/choices.py
nautobot_device_lifecycle_mgmt/contract_filters.py
nautobot_device_lifecycle_mgmt/filter_extensions.py
nautobot_device_lifecycle_mgmt/filters.py
nautobot_device_lifecycle_mgmt/forms.py
nautobot_device_lifecycle_mgmt/graphql/types.py
nautobot_device_lifecycle_mgmt/helpers.py
nautobot_device_lifecycle_mgmt/jobs/__init__.py
nautobot_device_lifecycle_mgmt/jobs/cve_tracking.py
nautobot_device_lifecycle_mgmt/jobs/lifecycle_reporting.py
nautobot_device_lifecycle_mgmt/jobs/model_migration.py
nautobot_device_lifecycle_mgmt/management/commands/generate_dlm_test_data.py
nautobot_device_lifecycle_mgmt/metrics.py
nautobot_device_lifecycle_mgmt/migrations/0001_hardwarelcm.py
nautobot_device_lifecycle_mgmt/migrations/0002_softwarelcm.py
nautobot_device_lifecycle_mgmt/migrations/0003_service_contracts.py
nautobot_device_lifecycle_mgmt/migrations/0004_squash__0004_0014_0015_0016.py
nautobot_device_lifecycle_mgmt/migrations/0004_validated_software_m2m.py
nautobot_device_lifecycle_mgmt/migrations/0005_software_reporting.py
nautobot_device_lifecycle_mgmt/migrations/0006_cvelcm_vulnerabilitylcm.py
nautobot_device_lifecycle_mgmt/migrations/0007_softwareimagelcm.py
nautobot_device_lifecycle_mgmt/migrations/0008_software_image_data_migration.py
nautobot_device_lifecycle_mgmt/migrations/0009_software_remove_image_fields.py
nautobot_device_lifecycle_mgmt/migrations/0010_softwareimagelcm_hash_algorithm.py
nautobot_device_lifecycle_mgmt/migrations/0011_add_valid_software_field_to_result.py
nautobot_device_lifecycle_mgmt/migrations/0012_add_related_name_to_results_model.py
nautobot_device_lifecycle_mgmt-3.2.2.dist-info/LICENSE
nautobot_device_lifecycle_mgmt-3.2.2.dist-info/METADATA
nautobot_device_lifecycle_mgmt-3.2.2.dist-info/WHEEL
nautobot_device_lifecycle_mgmt-3.2.2.dist-info/RECORD
