Metadata-Version: 2.3
Name: nautobot-device-lifecycle-mgmt
Version: 3.2.2
Summary: Manages device lifecycles for platforms and software.
License: Apache-2.0
Keywords: nautobot,nautobot-app,nautobot-plugin
Author: Network to Code, LLC
Author-email: info@networktocode.com
Requires-Python: >=3.10,<3.13
Classifier: Development Status :: 5 - Production/Stable
Classifier: Intended Audience :: Developers
Classifier: License :: OSI Approved :: Apache Software License
Classifier: Programming Language :: Python :: 3
Classifier: Programming Language :: Python :: 3.10
Classifier: Programming Language :: Python :: 3.11
Classifier: Programming Language :: Python :: 3.12
Provides-Extra: all
Requires-Dist: matplotlib (>=3.3.4,<4.0.0)
Requires-Dist: nautobot (>=2.4.20,<3.0.0)
Requires-Dist: netutils (>=1.14.1)
Requires-Dist: numpy (>=1.26,<2.0)
Requires-Dist: pycountry (>=22.3.5,<25.0.0)
Project-URL: Documentation, https://docs.nautobot.com/projects/device-lifecycle/en/latest/
Project-URL: Homepage, https://github.com/nautobot/nautobot-app-device-lifecycle-mgmt
Project-URL: Repository, https://github.com/nautobot/nautobot-app-device-lifecycle-mgmt
